oomodelling/Model.py
oomodelling/ModelSolver.py
oomodelling/TrackingSimulator.py
oomodelling/__init__.py
oomodelling/examples/ExampleModels.py
oomodelling/examples/ExampleTrackingSimulators.py
oomodelling/examples/IncubatorModels.py
oomodelling/examples/__init__.py
oomodelling-0.1.0.dist-info/LICENSE
oomodelling-0.1.0.dist-info/METADATA
oomodelling-0.1.0.dist-info/WHEEL
oomodelling-0.1.0.dist-info/top_level.txt
oomodelling-0.1.0.dist-info/RECORD
