Metadata-Version: 2.1
Name: oomodelling
Version: 0.1.0
Summary: An object oriented modelling package for causal models.
Home-page: https://gitlab.au.dk/clagms/oomodellingpython
Author: Claudio Gomes
Author-email: claudio.gomes@ece.au.dk
License: UNKNOWN
Platform: UNKNOWN
Classifier: Programming Language :: Python :: 3
Classifier: Operating System :: OS Independent
Requires-Python: >=3.6
License-File: LICENSE
Requires-Dist: numpy
Requires-Dist: matplotlib
Requires-Dist: scipy
Requires-Dist: deprecation
